filum_utils_dev/__init__.py
filum_utils_dev/config.py
filum_utils_dev/enums.py
filum_utils_dev/errors.py
filum_utils_dev/sentry.py
filum_utils_dev/clients/__init__.py
filum_utils_dev/clients/action.py
filum_utils_dev/clients/analytics.py
filum_utils_dev/clients/common.py
filum_utils_dev/clients/connection.py
filum_utils_dev/clients/filum.py
filum_utils_dev/clients/google.py
filum_utils_dev/clients/iam.py
filum_utils_dev/clients/log.py
filum_utils_dev/clients/mini_app.py
filum_utils_dev/clients/notification.py
filum_utils_dev/clients/segment.py
filum_utils_dev/clients/subscription.py
filum_utils_dev/services/__init__.py
filum_utils_dev/services/file.py
filum_utils_dev/services/subscription/__init__.py
filum_utils_dev/services/subscription/automated_action.py
filum_utils_dev/services/subscription/base_campaign.py
filum_utils_dev/services/subscription/campaign.py
filum_utils_dev/services/subscription/engagement_campaign.py
filum_utils_dev/types/__init__.py
filum_utils_dev/types/account.py
filum_utils_dev/types/action.py
filum_utils_dev/types/automated_action.py
filum_utils_dev/types/campaign.py
filum_utils_dev/types/common.py
filum_utils_dev/types/conversation.py
filum_utils_dev/types/engagement_campaign.py
filum_utils_dev/types/engagement_message.py
filum_utils_dev/types/mini_app.py
filum_utils_dev/types/organization.py
filum_utils_dev/types/segment.py
filum_utils_dev/types/subscription.py
filum_utils_dev/types/survey.py
filum_utils_dev/types/survey_response.py
filum_utils_dev/utils/__init__.py
filum_utils_dev/utils/datetime_formatter.py
filum_utils_dev/utils/segment_users.py
filum_utils_dev/utils/smart_distributions.py
filum_utils_dev/utils/string_formatter.py
filum_utils_dev/utils/automated_action/__init__.py
filum_utils_dev/utils/automated_action/enums.py
filum_utils_dev/utils/automated_action/string_formatter.py
filum_utils_dev/utils/engagement_campaign/__init__.py
filum_utils_dev/utils/engagement_campaign/string_formatter.py
tests/__init__.py
filum_utils_dev-0.0.5.dist-info/METADATA
filum_utils_dev-0.0.5.dist-info/WHEEL
filum_utils_dev-0.0.5.dist-info/top_level.txt
filum_utils_dev-0.0.5.dist-info/RECORD
