Metadata-Version: 2.1
Name: filum-utils-dev
Version: 0.0.5
Summary: Filum Utils Dev
Author: Long Nguyen
Author-email: <long@filum.ai>
Classifier: Development Status :: 3 - Alpha
Classifier: Intended Audience :: Developers
Classifier: Programming Language :: Python :: 2
Classifier: Programming Language :: Python :: 3
Classifier: Operating System :: OS Independent
Requires-Dist: requests ==2.31.0
Requires-Dist: sentry-sdk ==2.18.0
Requires-Dist: filum-analytics-python ==1.1.1
Requires-Dist: glom ==20.11.0
Requires-Dist: pyexcel ==0.7.0
Requires-Dist: pyexcel-xls ==0.7.0
Requires-Dist: pyexcel-xlsx ==0.6.0
Requires-Dist: openpyxl ==3.0.10
Requires-Dist: setuptools ==68.0.0
Requires-Dist: tenacity ==8.2.3
Requires-Dist: python-dateutil ==2.8.2
Requires-Dist: google-cloud-pubsub ==2.13.6
Requires-Dist: google-cloud-storage ==2.5.0
